odoo/addons/stock_inventory_chatter/README.rst
odoo/addons/stock_inventory_chatter/__init__.py
odoo/addons/stock_inventory_chatter/__manifest__.py
odoo/addons/stock_inventory_chatter/data/stock_data.xml
odoo/addons/stock_inventory_chatter/i18n/ar.po
odoo/addons/stock_inventory_chatter/i18n/bg.po
odoo/addons/stock_inventory_chatter/i18n/bs.po
odoo/addons/stock_inventory_chatter/i18n/ca.po
odoo/addons/stock_inventory_chatter/i18n/cs.po
odoo/addons/stock_inventory_chatter/i18n/cs_CZ.po
odoo/addons/stock_inventory_chatter/i18n/da.po
odoo/addons/stock_inventory_chatter/i18n/de.po
odoo/addons/stock_inventory_chatter/i18n/el_GR.po
odoo/addons/stock_inventory_chatter/i18n/en_GB.po
odoo/addons/stock_inventory_chatter/i18n/es.po
odoo/addons/stock_inventory_chatter/i18n/es_AR.po
odoo/addons/stock_inventory_chatter/i18n/es_CL.po
odoo/addons/stock_inventory_chatter/i18n/es_CO.po
odoo/addons/stock_inventory_chatter/i18n/es_CR.po
odoo/addons/stock_inventory_chatter/i18n/es_DO.po
odoo/addons/stock_inventory_chatter/i18n/es_EC.po
odoo/addons/stock_inventory_chatter/i18n/es_ES.po
odoo/addons/stock_inventory_chatter/i18n/es_MX.po
odoo/addons/stock_inventory_chatter/i18n/es_PE.po
odoo/addons/stock_inventory_chatter/i18n/es_PY.po
odoo/addons/stock_inventory_chatter/i18n/es_VE.po
odoo/addons/stock_inventory_chatter/i18n/et.po
odoo/addons/stock_inventory_chatter/i18n/eu.po
odoo/addons/stock_inventory_chatter/i18n/fa.po
odoo/addons/stock_inventory_chatter/i18n/fi.po
odoo/addons/stock_inventory_chatter/i18n/fr.po
odoo/addons/stock_inventory_chatter/i18n/gl.po
odoo/addons/stock_inventory_chatter/i18n/he.po
odoo/addons/stock_inventory_chatter/i18n/hr.po
odoo/addons/stock_inventory_chatter/i18n/hr_HR.po
odoo/addons/stock_inventory_chatter/i18n/hu.po
odoo/addons/stock_inventory_chatter/i18n/id.po
odoo/addons/stock_inventory_chatter/i18n/it.po
odoo/addons/stock_inventory_chatter/i18n/ja.po
odoo/addons/stock_inventory_chatter/i18n/ko.po
odoo/addons/stock_inventory_chatter/i18n/lt.po
odoo12_addon_stock_inventory_chatter-12.0.1.0.0.99.dev13.dist-info/METADATA
odoo12_addon_stock_inventory_chatter-12.0.1.0.0.99.dev13.dist-info/WHEEL
odoo12_addon_stock_inventory_chatter-12.0.1.0.0.99.dev13.dist-info/top_level.txt
odoo12_addon_stock_inventory_chatter-12.0.1.0.0.99.dev13.dist-info/RECORD
